sgclimaapiclient/__init__.py
sgclimaapiclient/baseapi.py
sgclimaapiclient/dataapi.py
sgclimaapiclient/modelsapi.py
sgclimaapiclient/version.py
sgclimaapiclient-1.1.44.dist-info/LICENSE
sgclimaapiclient-1.1.44.dist-info/METADATA
sgclimaapiclient-1.1.44.dist-info/WHEEL
sgclimaapiclient-1.1.44.dist-info/top_level.txt
sgclimaapiclient-1.1.44.dist-info/RECORD
