Metadata-Version: 2.1
Name: sgclimaapiclient
Version: 1.1.44
Summary: Module to use sgclimaapi from python
Home-page: 
Author: Indoorclima
Author-email: 
License-File: LICENSE
Requires-Dist: setuptools>=45.2.0
Requires-Dist: pandas>=1.2.0
Requires-Dist: numpy>=1.19.5
Requires-Dist: requests>=2.21.0
Requires-Dist: azure-storage-blob>=12.14.1
Requires-Dist: aiohttp>=3.5.1
Requires-Dist: fastparquet>=0.8.3
Requires-Dist: pyarrow>=21.0.0
